odoo/addons/stock_location_fill_state/README.rst
odoo/addons/stock_location_fill_state/__init__.py
odoo/addons/stock_location_fill_state/__manifest__.py
odoo/addons/stock_location_fill_state/i18n/fr.po
odoo/addons/stock_location_fill_state/i18n/it.po
odoo/addons/stock_location_fill_state/i18n/stock_location_fill_state.pot
odoo/addons/stock_location_fill_state/models/__init__.py
odoo/addons/stock_location_fill_state/models/stock_location.py
odoo/addons/stock_location_fill_state/readme/CONTEXT.md
odoo/addons/stock_location_fill_state/readme/CONTRIBUTORS.md
odoo/addons/stock_location_fill_state/readme/DESCRIPTION.md
odoo/addons/stock_location_fill_state/readme/USAGE.md
odoo/addons/stock_location_fill_state/static/description/fill_state.png
odoo/addons/stock_location_fill_state/static/description/icon.png
odoo/addons/stock_location_fill_state/static/description/index.html
odoo/addons/stock_location_fill_state/tests/__init__.py
odoo/addons/stock_location_fill_state/tests/common.py
odoo/addons/stock_location_fill_state/tests/test_location_fill_state.py
odoo/addons/stock_location_fill_state/views/stock_location.xml
odoo_addon_stock_location_fill_state-18.0.1.1.0.dist-info/METADATA
odoo_addon_stock_location_fill_state-18.0.1.1.0.dist-info/WHEEL
odoo_addon_stock_location_fill_state-18.0.1.1.0.dist-info/top_level.txt
odoo_addon_stock_location_fill_state-18.0.1.1.0.dist-info/RECORD
