Metadata-Version: 2.1
Name: odoo-addon-stock_location_fill_state
Version: 18.0.1.1.0
Requires-Python: >=3.10
Requires-Dist: odoo-addon-base_partition==18.0.*
Requires-Dist: odoo-addon-stock_location_pending_move==18.0.*
Requires-Dist: odoo==18.0.*
Summary: This module allows to identify the fill state of stock locations
Home-page: https://github.com/OCA/stock-logistics-warehouse
License: AGPL-3
Author: ACSONE SA/NV, BCIM, Odoo Community Association (OCA)
Author-email: support@odoo-community.org
Classifier: Programming Language :: Python
Classifier: Framework :: Odoo
Classifier: Framework :: Odoo :: 18.0
Classifier: License :: OSI Approved :: GNU Affero General Public License v3
